cardda_python/.coverage
cardda_python/__init__.py
cardda_python/banking.py
cardda_python/client.py
cardda_python/constants.py
cardda_python/http_client.py
cardda_python/resources/__init__.py
cardda_python/resources/bank_account.py
cardda_python/resources/bank_key.py
cardda_python/resources/bank_payroll.py
cardda_python/resources/bank_recipient.py
cardda_python/resources/bank_transaction.py
cardda_python/resources/base_resource.py
cardda_python/services/banking/__init__.py
cardda_python/services/banking/bank_account_service.py
cardda_python/services/banking/bank_key_service.py
cardda_python/services/banking/bank_payroll_service.py
cardda_python/services/banking/bank_recipient_service.py
cardda_python/services/banking/bank_transaction_service.py
cardda_python/services/base_service.py
cardda_python-0.1.6.dist-info/LICENSE
cardda_python-0.1.6.dist-info/METADATA
cardda_python-0.1.6.dist-info/WHEEL
cardda_python-0.1.6.dist-info/RECORD
