Metadata-Version: 2.1
Name: cardda-python
Version: 0.1.6
Summary: This library wraps the api provided by Cardda to its customers.
Home-page: https://github.com/cardda/cardda_python
Author: danckoo1
Author-email: dancko.fernandez@uc.cl
Requires-Python: >=3.6,<4.0
Classifier: Environment :: Web Environment
Classifier: Intended Audience :: Developers
Classifier: Operating System :: OS Independent
Classifier: Programming Language :: Python :: 3
Classifier: Programming Language :: Python :: 3.6
Classifier: Programming Language :: Python :: 3.7
Classifier: Programming Language :: Python :: 3.8
Classifier: Programming Language :: Python :: 3.9
Classifier: Programming Language :: Python :: 3.10
Classifier: Programming Language :: Python :: 3.11
Classifier: Programming Language :: Python :: 3 :: Only
Requires-Dist: httpx (>=0.22,<0.23)
Project-URL: Repository, https://github.com/cardda/cardda_python
